melenium/__init__.py
melenium/__version__.py
melenium/wait_for.py
melenium/webdriver.py
melenium/common/capabilities.py
melenium/common/presets.py
melenium-0.1.0.dist-info/LICENSE
melenium-0.1.0.dist-info/METADATA
melenium-0.1.0.dist-info/WHEEL
melenium-0.1.0.dist-info/top_level.txt
melenium-0.1.0.dist-info/RECORD
