Metadata-Version: 2.1
Name: melenium
Version: 0.1.0
Summary: Routine automation.
Home-page: https://github.com/a-maliarov/melenium
Author: Anatolii Maliarov
Author-email: tly.mov@gmail.com
License: UNKNOWN
Project-URL: Documentation, https://github.com/a-maliarov/melenium
Project-URL: Source, https://github.com/a-maliarov/melenium
Platform: UNKNOWN
Classifier: License :: OSI Approved :: MIT License
Classifier: Operating System :: OS Independent
Classifier: Development Status :: 1 - Planning
Classifier: Natural Language :: English
Classifier: Intended Audience :: Developers
Classifier: Intended Audience :: Education
Classifier: Intended Audience :: Information Technology
Requires-Dist: selenium (~=3.141.0)
Requires-Dist: bs4 (~=0.0.1)
Requires-Dist: beautifulsoup4 (~=4.9.3)
Requires-Dist: pyaction (~=0.1.0)
Requires-Dist: selenium-wire (~=2.1.2)
